flask_aad/__init__.py
flask_aad/autherror.py
flask_aad/tokenhandler.py
evonik_flask_aad-0.0.2.dist-info/LICENSE
evonik_flask_aad-0.0.2.dist-info/METADATA
evonik_flask_aad-0.0.2.dist-info/WHEEL
evonik_flask_aad-0.0.2.dist-info/top_level.txt
evonik_flask_aad-0.0.2.dist-info/RECORD
