Metadata-Version: 2.1
Name: evonik-flask-aad
Version: 0.0.2
Summary: Azure Active Directory Helper for Flask or connexion applications
Home-page: https://www.evonik.com
Author: Sven Igl
Author-email: sven-alexander.igl@evonik.com
License: UNKNOWN
Platform: UNKNOWN
Classifier: Programming Language :: Python :: 3
Classifier: License :: OSI Approved :: MIT License
Classifier: Operating System :: OS Independent
Requires-Python: >=3.6
Requires-Dist: python-jose
Requires-Dist: six
Requires-Dist: flask
